lds_weixin/__init__.py
lds_weixin/api.py
lds_weixin/base.py
lds_weixin/exception.py
lds_weixin/utils.py
lds_weixin/versions.py
lds_weixin-0.0.11.dist-info/METADATA
lds_weixin-0.0.11.dist-info/WHEEL
lds_weixin-0.0.11.dist-info/top_level.txt
lds_weixin-0.0.11.dist-info/RECORD
