Metadata-Version: 2.4
Name: lds_weixin
Version: 0.0.11
Summary: 企业微信Api接口
Home-page: https://github.com/ldsxp
Download-URL: https://pypi.org/project/lds_weixin
Author: lds
Author-email: 85176878@qq.com
License: GNU GPL 3
Platform: any
Classifier: Development Status :: 5 - Production/Stable
Classifier: Intended Audience :: Developers
Classifier: License :: OSI Approved :: GNU General Public License (GPL)
Classifier: Operating System :: OS Independent
Classifier: Programming Language :: Python
Classifier: Programming Language :: Python :: 3.6
Requires-Dist: requests
Dynamic: author
Dynamic: author-email
Dynamic: classifier
Dynamic: description
Dynamic: description-content-type
Dynamic: download-url
Dynamic: home-page
Dynamic: license
Dynamic: platform
Dynamic: requires-dist
Dynamic: summary
